{
  "latest_stable": {
    "version": "6.7.8"
  },
  "releases": [
    {
      "iseol": false,
      "version": "6.8-rc6",
      "moniker": "mainline",
      "source": "https://git.kernel.org/torvalds/t/linux-6.8-rc6.tar.gz",
      "pgp": null,
      "released": {
        "timestamp": 1708904766,
        "isodate": "2024-02-25"
      },
      "gitweb": "https://git.kernel.org/torvalds/h/v6.8-rc6",
      "changelog": null,
      "diffview": "https://git.kernel.org/torvalds/ds/v6.8-rc6/v6.8-rc5",
      "patch": {
        "full": "https://git.kernel.org/torvalds/p/v6.8-rc6/v6.7",
        "incremental": "https://git.kernel.org/torvalds/p/v6.8-rc6/v6.8-rc5"
      }
    },
    {
      "iseol": false,
      "version": "6.7.8",
      "moniker": "stable",
      "source": "https://cdn.kernel.org/pub/linux/kernel/v6.x/linux-6.7.8.tar.xz",
      "pgp": "https://cdn.kernel.org/pub/linux/kernel/v6.x/linux-6.7.8.tar.sign",
      "released": {
        "timestamp": 1709400455,
        "isodate": "2024-03-02"
      },
      "gitweb": "https://git.kernel.org/stable/h/v6.7.8",
      "changelog": "https://cdn.kernel.org/pub/linux/kernel/v6.x/ChangeLog-6.7.8",
      "diffview": "https://git.kernel.org/stable/ds/v6.7.8/v6.7.7",
      "patch": {
        "full": "https://cdn.kernel.org/pub/linux/kernel/v6.x/patch-6.7.8.xz",
        "incremental": "https://cdn.kernel.org/pub/linux/kernel/v6.x/incr/patch-6.7.7-8.xz"
      }
    },
    {
      "iseol": false,
      "version": "6.6.20",
      "moniker": "longterm",
      "source": "https://cdn.kernel.org/pub/linux/kernel/v6.x/linux-6.6.20.tar.xz",
      "pgp": "https://cdn.kernel.org/pub/linux/kernel/v6.x/linux-6.6.20.tar.sign",
      "released": {
        "timestamp": 1709400194,
        "isodate": "2024-03-02"
      },
      "gitweb": "https://git.kernel.org/stable/h/v6.6.20",
      "changelog": "https://cdn.kernel.org/pub/linux/kernel/v6.x/ChangeLog-6.6.20",
      "diffview": "https://git.kernel.org/stable/ds/v6.6.20/v6.6.19",
      "patch": {
        "full": "https://cdn.kernel.org/pub/linux/kernel/v6.x/patch-6.6.20.xz",
        "incremental": "https://cdn.kernel.org/pub/linux/kernel/v6.x/incr/patch-6.6.19-20.xz"
      }
    },
    {
      "iseol": false,
      "version": "6.1.80",
      "moniker": "longterm",
      "source": "https://cdn.kernel.org/pub/linux/kernel/v6.x/linux-6.1.80.tar.xz",
      "pgp": "https://cdn.kernel.org/pub/linux/kernel/v6.x/linux-6.1.80.tar.sign",
      "released": {
        "timestamp": 1709296034,
        "isodate": "2024-03-01"
      },
      "gitweb": "https://git.kernel.org/stable/h/v6.1.80",
      "changelog": "https://cdn.kernel.org/pub/linux/kernel/v6.x/ChangeLog-6.1.80",
      "diffview": "https://git.kernel.org/stable/ds/v6.1.80/v6.1.79",
      "patch": {
        "full": "https://cdn.kernel.org/pub/linux/kernel/v6.x/patch-6.1.80.xz",
        "incremental": "https://cdn.kernel.org/pub/linux/kernel/v6.x/incr/patch-6.1.79-80.xz"
      }
    },
    {
      "iseol": false,
      "version": "5.15.150",
      "moniker": "longterm",
      "source": "https://cdn.kernel.org/pub/linux/kernel/v5.x/linux-5.15.150.tar.xz",
      "pgp": "https://cdn.kernel.org/pub/linux/kernel/v5.x/linux-5.15.150.tar.sign",
      "released": {
        "timestamp": 1709295747,
        "isodate": "2024-03-01"
      },
      "gitweb": "https://git.kernel.org/stable/h/v5.15.150",
      "changelog": "https://cdn.kernel.org/pub/linux/kernel/v5.x/ChangeLog-5.15.150",
      "diffview": "https://git.kernel.org/stable/ds/v5.15.150/v5.15.149",
      "patch": {
        "full": "https://cdn.kernel.org/pub/linux/kernel/v5.x/patch-5.15.150.xz",
        "incremental": "https://cdn.kernel.org/pub/linux/kernel/v5.x/incr/patch-5.15.149-150.xz"
      }
    },
    {
      "iseol": false,
      "version": "5.10.211",
      "moniker": "longterm",
      "source": "https://cdn.kernel.org/pub/linux/kernel/v5.x/linux-5.10.211.tar.xz",
      "pgp": "https://cdn.kernel.org/pub/linux/kernel/v5.x/linux-5.10.211.tar.sign",
      "released": {
        "timestamp": 1709295417,
        "isodate": "2024-03-01"
      },
      "gitweb": "https://git.kernel.org/stable/h/v5.10.211",
      "changelog": "https://cdn.kernel.org/pub/linux/kernel/v5.x/ChangeLog-5.10.211",
      "diffview": "https://git.kernel.org/stable/ds/v5.10.211/v5.10.210",
      "patch": {
        "full": "https://cdn.kernel.org/pub/linux/kernel/v5.x/patch-5.10.211.xz",
        "incremental": "https://cdn.kernel.org/pub/linux/kernel/v5.x/incr/patch-5.10.210-211.xz"
      }
    },
    {
      "iseol": false,
      "version": "5.4.270",
      "moniker": "longterm",
      "source": "https://cdn.kernel.org/pub/linux/kernel/v5.x/linux-5.4.270.tar.xz",
      "pgp": "https://cdn.kernel.org/pub/linux/kernel/v5.x/linux-5.4.270.tar.sign",
      "released": {
        "timestamp": 1709295222,
        "isodate": "2024-03-01"
      },
      "gitweb": "https://git.kernel.org/stable/h/v5.4.270",
      "changelog": "https://cdn.kernel.org/pub/linux/kernel/v5.x/ChangeLog-5.4.270",
      "diffview": "https://git.kernel.org/stable/ds/v5.4.270/v5.4.269",
      "patch": {
        "full": "https://cdn.kernel.org/pub/linux/kernel/v5.x/patch-5.4.270.xz",
        "incremental": "https://cdn.kernel.org/pub/linux/kernel/v5.x/incr/patch-5.4.269-270.xz"
      }
    },
    {
      "iseol": false,
      "version": "4.19.308",
      "moniker": "longterm",
      "source": "https://cdn.kernel.org/pub/linux/kernel/v4.x/linux-4.19.308.tar.xz",
      "pgp": "https://cdn.kernel.org/pub/linux/kernel/v4.x/linux-4.19.308.tar.sign",
      "released": {
        "timestamp": 1709294776,
        "isodate": "2024-03-01"
      },
      "gitweb": "https://git.kernel.org/stable/h/v4.19.308",
      "changelog": "https://cdn.kernel.org/pub/linux/kernel/v4.x/ChangeLog-4.19.308",
      "diffview": "https://git.kernel.org/stable/ds/v4.19.308/v4.19.307",
      "patch": {
        "full": "https://cdn.kernel.org/pub/linux/kernel/v4.x/patch-4.19.308.xz",
        "incremental": "https://cdn.kernel.org/pub/linux/kernel/v4.x/incr/patch-4.19.307-308.xz"
      }
    },
    {
      "iseol": false,
      "version": "next-20240301",
      "moniker": "linux-next",
      "source": null,
      "pgp": null,
      "released": {
        "timestamp": 1709272450,
        "isodate": "2024-03-01"
      },
      "gitweb": "https://git.kernel.org/next/linux-next/h/next-20240301",
      "changelog": null,
      "diffview": null,
      "patch": {
        "full": null,
        "incremental": null
      }
    }
  ]
}